{"s:intro": {"slug": "intro", "text": "Chapter", "value": "1"}, "s:intro-personas": {"slug": "intro", "text": "Section", "value": "1.1"}, "s:intro-setup": {"slug": "intro", "text": "Section", "value": "1.2"}, "s:intro-contributors": {"slug": "intro", "text": "Section", "value": "1.3"}, "s:intro-exercises": {"slug": "intro", "text": "Section", "value": "1.4"}, "s:basics": {"slug": "basics", "text": "Chapter", "value": "2"}, "s:basics-hello-world": {"slug": "basics", "text": "Section", "value": "2.1"}, "s:basics-data-types": {"slug": "basics", "text": "Section", "value": "2.2"}, "s:basics-control-flow": {"slug": "basics", "text": "Section", "value": "2.3"}, "s:basics-formatting": {"slug": "basics", "text": "Section", "value": "2.4"}, "s:basics-objects": {"slug": "basics", "text": "Section", "value": "2.5"}, "s:basics-functions": {"slug": "basics", "text": "Section", "value": "2.6"}, "s:basics-modules": {"slug": "basics", "text": "Section", "value": "2.7"}, "s:basics-exercises": {"slug": "basics", "text": "Section", "value": "2.8"}, "s:callbacks": {"slug": "callbacks", "text": "Chapter", "value": "3"}, "s:callbacks-callstack": {"slug": "callbacks", "text": "Section", "value": "3.1"}, "s:callbacks-func": {"slug": "callbacks", "text": "Section", "value": "3.2"}, "s:callbacks-anonymous": {"slug": "callbacks", "text": "Section", "value": "3.3"}, "s:callbacks-functional": {"slug": "callbacks", "text": "Section", "value": "3.4"}, "s:callbacks-closures": {"slug": "callbacks", "text": "Section", "value": "3.5"}, "s:callbacks-exercises": {"slug": "callbacks", "text": "Section", "value": "3.6"}, "f:callbacks-name-value": {"slug": "callbacks", "text": "Figure", "value": "1"}, "f:callbacks-one-more": {"slug": "callbacks", "text": "Figure", "value": "2"}, "f:callbacks-alias-function": {"slug": "callbacks", "text": "Figure", "value": "3"}, "f:callbacks-call-stack": {"slug": "callbacks", "text": "Figure", "value": "4"}, "f:callbacks-do-twice": {"slug": "callbacks", "text": "Figure", "value": "5"}, "f:callbacks-pipeline": {"slug": "callbacks", "text": "Figure", "value": "6"}, "f:callbacks-adder-1": {"slug": "callbacks", "text": "Figure", "value": "7"}, "f:callbacks-adder-2": {"slug": "callbacks", "text": "Figure", "value": "8"}, "f:callbacks-adder-3": {"slug": "callbacks", "text": "Figure", "value": "9"}, "f:callbacks-adder-4": {"slug": "callbacks", "text": "Figure", "value": "10"}, "s:oop": {"slug": "oop", "text": "Chapter", "value": "4"}, "s:oop-manual": {"slug": "oop", "text": "Section", "value": "4.1"}, "s:oop-classes": {"slug": "oop", "text": "Section", "value": "4.2"}, "s:oop-inheritance": {"slug": "oop", "text": "Section", "value": "4.3"}, "s:oop-protocols": {"slug": "oop", "text": "Section", "value": "4.4"}, "s:oop-exercises": {"slug": "oop", "text": "Section", "value": "4.5"}, "f:oop-inheritance": {"slug": "oop", "text": "Figure", "value": "11"}, "s:htmlcss": {"slug": "htmlcss", "text": "Chapter", "value": "5"}, "s:htmlcss-formatting": {"slug": "htmlcss", "text": "Section", "value": "5.1"}, "s:htmlcss-text": {"slug": "htmlcss", "text": "Section", "value": "5.2"}, "s:htmlcss-pages": {"slug": "htmlcss", "text": "Section", "value": "5.3"}, "s:htmlcss-attributes": {"slug": "htmlcss", "text": "Section", "value": "5.4"}, "s:htmlcss-lists": {"slug": "htmlcss", "text": "Section", "value": "5.5"}, "s:htmlcss-tables": {"slug": "htmlcss", "text": "Section", "value": "5.6"}, "s:htmlcss-links": {"slug": "htmlcss", "text": "Section", "value": "5.7"}, "s:htmlcss-images": {"slug": "htmlcss", "text": "Section", "value": "5.8"}, "s:htmlcss-css": {"slug": "htmlcss", "text": "Section", "value": "5.9"}, "s:htmlcss-bootstrap": {"slug": "htmlcss", "text": "Section", "value": "5.10"}, "s:htmlcss-exercises": {"slug": "htmlcss", "text": "Section", "value": "5.11"}, "s:pages": {"slug": "pages", "text": "Chapter", "value": "6"}, "s:pages-counting": {"slug": "pages", "text": "Section", "value": "6.1"}, "s:pages-toc": {"slug": "pages", "text": "Section", "value": "6.2"}, "s:pages-sort-list": {"slug": "pages", "text": "Section", "value": "6.3"}, "s:pages-citations": {"slug": "pages", "text": "Section", "value": "6.4"}, "s:pages-clock": {"slug": "pages", "text": "Section", "value": "6.5"}, "s:pages-exercises": {"slug": "pages", "text": "Section", "value": "6.6"}, "s:dynamic": {"slug": "dynamic", "text": "Chapter", "value": "7"}, "s:dynamic-hello": {"slug": "dynamic", "text": "Section", "value": "7.1"}, "s:dynamic-jsx": {"slug": "dynamic", "text": "Section", "value": "7.2"}, "s:dynamic-components": {"slug": "dynamic", "text": "Section", "value": "7.3"}, "s:dynamic-parcel": {"slug": "dynamic", "text": "Section", "value": "7.4"}, "s:dynamic-multiple": {"slug": "dynamic", "text": "Section", "value": "7.5"}, "s:dynamic-exercises": {"slug": "dynamic", "text": "Section", "value": "7.6"}, "f:dynamic-alternatives": {"slug": "dynamic", "text": "Figure", "value": "12"}, "s:vis": {"slug": "vis", "text": "Chapter", "value": "8"}, "s:vis-vega-lite": {"slug": "vis", "text": "Section", "value": "8.1"}, "s:vis-vega-local": {"slug": "vis", "text": "Section", "value": "8.2"}, "s:vis-exercises": {"slug": "vis", "text": "Section", "value": "8.3"}, "f:vis-mark-encoding": {"slug": "vis", "text": "Figure", "value": "13"}, "f:vis-disable-controls": {"slug": "vis", "text": "Figure", "value": "14"}, "f:vis-aggregate-points": {"slug": "vis", "text": "Figure", "value": "15"}, "s:promises": {"slug": "promises", "text": "Chapter", "value": "9"}, "s:promises-queue": {"slug": "promises", "text": "Section", "value": "9.1"}, "s:promises-promises": {"slug": "promises", "text": "Section", "value": "9.2"}, "s:promises-usage": {"slug": "promises", "text": "Section", "value": "9.3"}, "s:promises-async-await": {"slug": "promises", "text": "Section", "value": "9.4"}, "s:promises-exercises": {"slug": "promises", "text": "Section", "value": "9.5"}, "f:promises-queue": {"slug": "promises", "text": "Figure", "value": "16"}, "f:promises-object-a": {"slug": "promises", "text": "Figure", "value": "17"}, "f:promises-object-b": {"slug": "promises", "text": "Figure", "value": "18"}, "s:interactive": {"slug": "interactive", "text": "Chapter", "value": "10"}, "s:interactive-babel": {"slug": "interactive", "text": "Section", "value": "10.1"}, "s:interactive-models-views": {"slug": "interactive", "text": "Section", "value": "10.2"}, "s:interactive-fetching": {"slug": "interactive", "text": "Section", "value": "10.3"}, "s:interactive-exercises": {"slug": "interactive", "text": "Section", "value": "10.4"}, "f:interactive-objects-dom": {"slug": "interactive", "text": "Figure", "value": "19"}, "f:interactive-asteroids-screenshot": {"slug": "interactive", "text": "Figure", "value": "20"}, "s:dataman": {"slug": "dataman", "text": "Chapter", "value": "11"}, "s:dataman-formats": {"slug": "dataman", "text": "Section", "value": "11.1"}, "s:dataman-slicing": {"slug": "dataman", "text": "Section", "value": "11.2"}, "s:dataman-manager": {"slug": "dataman", "text": "Section", "value": "11.3"}, "s:dataman-exercises": {"slug": "dataman", "text": "Section", "value": "11.4"}, "s:server": {"slug": "server", "text": "Chapter", "value": "12"}, "s:server-http": {"slug": "server", "text": "Section", "value": "12.1"}, "s:server-express": {"slug": "server", "text": "Section", "value": "12.2"}, "s:server-paths": {"slug": "server", "text": "Section", "value": "12.3"}, "s:server-files": {"slug": "server", "text": "Section", "value": "12.4"}, "s:server-content-types": {"slug": "server", "text": "Section", "value": "12.5"}, "s:server-exercises": {"slug": "server", "text": "Section", "value": "12.6"}, "f:server-cycle": {"slug": "server", "text": "Figure", "value": "21"}, "f:server-request": {"slug": "server", "text": "Figure", "value": "22"}, "s:testing": {"slug": "testing", "text": "Chapter", "value": "13"}, "s:testing-mocha": {"slug": "testing", "text": "Section", "value": "13.1"}, "s:testing-refactoring": {"slug": "testing", "text": "Section", "value": "13.2"}, "s:testing-server": {"slug": "testing", "text": "Section", "value": "13.3"}, "s:testing-html": {"slug": "testing", "text": "Section", "value": "13.4"}, "s:testing-exercises": {"slug": "testing", "text": "Section", "value": "13.5"}, "s:capstone": {"slug": "capstone", "text": "Chapter", "value": "14"}, "s:capstone-data": {"slug": "capstone", "text": "Section", "value": "14.1"}, "s:capstone-server": {"slug": "capstone", "text": "Section", "value": "14.2"}, "s:capstone-api": {"slug": "capstone", "text": "Section", "value": "14.3"}, "s:capstone-display": {"slug": "capstone", "text": "Section", "value": "14.4"}, "s:capstone-tables": {"slug": "capstone", "text": "Section", "value": "14.5"}, "s:capstone-chart": {"slug": "capstone", "text": "Section", "value": "14.6"}, "s:capstone-run": {"slug": "capstone", "text": "Section", "value": "14.7"}, "s:capstone-exercises": {"slug": "capstone", "text": "Section", "value": "14.8"}, "f:capstone-first-attempt": {"slug": "capstone", "text": "Figure", "value": "23"}, "f:capstone-second-attempt": {"slug": "capstone", "text": "Figure", "value": "24"}, "f:capstone-complete": {"slug": "capstone", "text": "Figure", "value": "25"}, "s:finale": {"slug": "finale", "text": "Chapter", "value": "15"}, "s:license": {"slug": "license", "text": "Appendix", "value": "A"}, "s:conduct": {"slug": "conduct", "text": "Appendix", "value": "B"}, "s:conduct-standards": {"slug": "conduct", "text": "Section", "value": "B.1"}, "s:conduct-responsibilities": {"slug": "conduct", "text": "Section", "value": "B.2"}, "s:conduct-scope": {"slug": "conduct", "text": "Section", "value": "B.3"}, "s:conduct-enforcement": {"slug": "conduct", "text": "Section", "value": "B.4"}, "s:conduct-attribution": {"slug": "conduct", "text": "Section", "value": "B.5"}, "s:citation": {"slug": "citation", "text": "Appendix", "value": "C"}, "s:contributing": {"slug": "contributing", "text": "Appendix", "value": "D"}, "s:gloss": {"slug": "gloss", "text": "Appendix", "value": "E"}, "s:keypoints": {"slug": "keypoints", "text": "Appendix", "value": "F"}, "s:legacy": {"slug": "legacy", "text": "Appendix", "value": "G"}, "s:legacy-equality": {"slug": "legacy", "text": "Section", "value": "G.1"}, "s:legacy-iteration": {"slug": "legacy", "text": "Section", "value": "G.2"}, "s:legacy-prototypes": {"slug": "legacy", "text": "Section", "value": "G.3"}, "f:legacy-prototype": {"slug": "legacy", "text": "Figure", "value": "26"}, "s:logging": {"slug": "logging", "text": "Appendix", "value": "H"}, "s:db": {"slug": "db", "text": "Appendix", "value": "I"}, "s:db-start": {"slug": "db", "text": "Section", "value": "I.1"}, "s:db-in-memory": {"slug": "db", "text": "Section", "value": "I.2"}, "s:db-testable": {"slug": "db", "text": "Section", "value": "I.3"}, "s:db-testing": {"slug": "db", "text": "Section", "value": "I.4"}, "s:db-mutate": {"slug": "db", "text": "Section", "value": "I.5"}, "s:db-exercises": {"slug": "db", "text": "Section", "value": "I.6"}, "s:extensible": {"slug": "extensible", "text": "Appendix", "value": "J"}}